{
  "home": {
    "Up_Your": "Up Your",
    "Digital_Design_Skills": "Digital Design Skills",
    "To_Advance_Your_Career_Path": "To Advance Your Career Path",
    "Hero_descr": "Provides you with the latest online learning system and material that help your digital design knowledge growing.",
    "Get_Started": "Get Started",
    "Course_Categories": "Course Categories",
    "Course_Categories_sub": "Fostering a playful & engaging learning environment",
    "UIUX_Design": "UI/UX Design",
    "UIUX_Descr": "Lessons on design that cover the most recent developments.",
    "Learn_More": "Learn More",
    "ThreeD_Modeling": "3D Modeling",
    "ThreeD_Descr": "3D Modeling courses that cover the most recent 3D trends.",
    "Video_Editing": "Video Editing",
    "Video_Descr": "Lessons in video editing learning form offline editing to special effects.",
    "Explore_All_Cat": "Explore All Category",
    "Explore_Programs": "Explore Programs",
    "Most_Popular": "Our Most Popular Programs",
    "Explore_Programs_desc": "Let's join our famous courses, the knowledge provided will definitely be useful for your career.",
    "Explore_All_Programs": "Explore All Programs",
    "Tutors": "Tutors",
    "Tutors_Heroes": "Meet the Heroes",
    "Tutors_descr": "On XLearners, instructors from all over the world instruct millions of students. We offer the knowledge and abilities.",
    "Footer_descr": "Top learning experiences that create more talent in the world.",
    "Browse_Course": "Browse Course",
    "All_Course": "All Courses",
    "WebDesign": "WebDesign",
    "UIUX_Design_Courses": "UI/UX Design Courses",
    "Graphic_Design": "Graphic Design Courses",
    "ThreeD_Modelling_Courses": "3D Modelling Courses",
    "Video_Editing_Courses": "Video Editing Courses",
    "Footer_Company": "Company",
    "Footer_About": "About us",
    "Footer_Contact": "Contact us",
    "Footer_Legal": "Legal",
    "Footer_Terms": "Terms of use",
    "Footer_Privacy": "Privacy policy",
    "Footer_Cookies": "Cookies policy",
    "Copyright": "Copyright © 2023 - All right reserved by XLearners"
  },
  "register": {
    "title": "Register and Start Learning",
    "send_offers": "Send me special offers, recommendations and learning tips.",
    "T_C": "By signing up, you agree to our Terms of Use and Privacy Policy.",
    "hv_acc": "Already have an account ?"
  },
  "login": {
    "log_in": "Login",
    "or": "Or",
    "forgot_password": "Forgot Password",
    "hv_acc": "Don't have an account ?",
    "signup": "Sign up"
  },
  "user": {
    "changePwPage": {
      "toast_not_match": "Passwords do not match",
      "toast_updated": "password updated successfully",
      "toast_failed": "password update failed try again later",
      "Change_Password": "Change Password",
      "Old_Password": "Old Password",
      "New_Password": "New Password",
      "Confirm_Password": "Confirm Password",
      "Save_Changes": "Save Changes"
    }
  }
}
